Metadata-Version: 1.1
Name: nblibrarian
Version: 0.0.1
Summary: nblibrarian: a utility for fetching notebooks from a source repository
Home-page: http://github.com/lheagy/nblibrarian
Author: Lindsey Heagy
Author-email: lindseyheagy@gmail.com
License: 3-clause BSD
Download-URL: http://github.com/lheagy/nblibrarian
Keywords: jupyter notebooks
Platform: Windows
Platform: Linux
Platform: Solaris
Platform: Mac OS-X
Platform: Unix
Classifier: Development Status :: 4 - Beta
Classifier: Intended Audience :: Developers
Classifier: Intended Audience :: Science/Research
Classifier: License :: OSI Approved :: BSD License
Classifier: Programming Language :: Python
Classifier: Operating System :: Microsoft :: Windows
Classifier: Operating System :: POSIX
Classifier: Operating System :: Unix
Classifier: Operating System :: MacOS
Classifier: Natural Language :: English
